jerome/__init__.py
jerome/__version__.py
jerome/common.py
jerome/glosser.py
jerome/keeper.py
jerome/loader.py
jerome/replacer.py
jerome/runlength.py
jerome/sample_text.py
jerome/bw/__init__.py
jerome/bw/burrowswheeler.py
jerome-0.3.0.dist-info/LICENSE
jerome-0.3.0.dist-info/METADATA
jerome-0.3.0.dist-info/WHEEL
jerome-0.3.0.dist-info/top_level.txt
jerome-0.3.0.dist-info/RECORD
