Metadata-Version: 2.1
Name: jerome
Version: 0.3.0
Summary: String Processing Tools
Home-page: https://github.com/kajuberdut/jerome
Author: Patrick Shechet
Author-email: patrick.shechet@gmail.com
License: MIT
Platform: UNKNOWN
Classifier: Development Status :: 3 - Alpha
Classifier: License :: OSI Approved :: BSD License
Classifier: Programming Language :: Python :: 3.8
Classifier: Programming Language :: Python :: 3 :: Only
License-File: LICENSE
